{
  "title": "Cars Data",
  "width": 500,
  "height": 500,
  "depth": 500,
  "data": {
    "url": "cars.json" 
  },
  "mark": "sphere",
  "encoding": {
    "x": {
      "field": "Horsepower",
      "type": "quantitative"
    },
    "y": {
      "field": "Miles_per_Gallon",
      "type": "quantitative"
    },
    "z": {
      "field": "Displacement",
      "type": "quantitative"
    },
    "color": {
      "field": "Origin",
      "type": "nominal"
    }
  },
  "portals": {
    "values": [
      {
        "x": -2000,
        "xrot": -6,
        "yrot": 82
      },
      {
        "z": -3000,
        "xrot": -4
      }
    ]
  }
}