{
  "title": "Field Data",
  "width": 500,
  "height": 500,
  "depth":  500,
  "data": { "url": "DxRData/cfd.json" },
  "mark": "paperplane",
  "encoding": {
    "x": {
      "field": "x",
      "type": "quantitative",
      "scale": {
        "domain": [ "20", "25" ]
      }
    },
    "y": {
      "field": "y",
      "type": "quantitative",
      "scale": {
        "domain": [ "20", "25" ]
      }
    },
    "z": {
      "field": "z",
      "type": "quantitative"
    },
    "xorient": {
      "field": "vx",
      "type": "quantitative",
      "scale": {
        "type": "none"
      }
    },
    "yorient": {
      "field": "vy",
      "type": "quantitative",
      "scale": {
        "type": "none"
      }
    },
    "zorient": {
      "field": "vz",
      "type": "quantitative",
      "scale": {
        "type": "none"
      }
    },
    "size": {
      "field": "vmag",
      "type": "quantitative",
      "scale": {
        "type": "linear",
        "domain": [ "0", "1" ],
        "range": [ "0", "30" ]
      }
    },
    "color": {
      "field": "vmag",
      "type": "quantitative"
    }
  }
}